<?xml version="1.0" encoding="UTF-8"?>
<Defs>

	<!-- produce -->

	<RecipeDef ParentName="MakeshiftAnimalArmorProductionBase">
		<defName>MakeMakeshiftAnimalArmorTiny</defName>
		<label>make makeshift animal armor (tiny)</label>
		<description>Make a set of makeshift animal armor out of steel.\n\nFits on animals with a mature body size of less than 0.3.</description>
		<workAmount>1750</workAmount>
		<ingredients>
			<li>
				<filter>
					<thingDefs>
						<li>Steel</li>
					</thingDefs>
				</filter>
				<count>35</count>
			</li>
		</ingredients>
		<products>
			<MakeshiftAnimalArmorTiny>1</MakeshiftAnimalArmorTiny>
		</products>
	</RecipeDef>

	<RecipeDef ParentName="MakeshiftAnimalArmorProductionBase">
		<defName>MakeMakeshiftAnimalArmorSmall</defName>
		<label>make makeshift animal armor (small)</label>
		<description>Make a set of makeshift animal armor out of steel.\n\nFits on animals with a mature body size of 0.3 or greater, but less than 0.7.</description>
		<workAmount>3500</workAmount>
		<ingredients>
			<li>
				<filter>
					<thingDefs>
						<li>Steel</li>
					</thingDefs>
				</filter>
				<count>70</count>
			</li>
		</ingredients>
		<products>
			<MakeshiftAnimalArmorSmall>1</MakeshiftAnimalArmorSmall>
		</products>
	</RecipeDef>

	<RecipeDef ParentName="MakeshiftAnimalArmorProductionBase">
		<defName>MakeMakeshiftAnimalArmorMedium</defName>
		<label>make makeshift animal armor (medium)</label>
		<description>Make a set of makeshift animal armor out of steel.\n\nFits on animals with a mature body size of 0.7 or greater, but less than 1.3.</description>
		<workAmount>6000</workAmount>
		<ingredients>
			<li>
				<filter>
					<thingDefs>
						<li>Steel</li>
					</thingDefs>
				</filter>
				<count>120</count>
			</li>
		</ingredients>
		<products>
			<MakeshiftAnimalArmorMedium>1</MakeshiftAnimalArmorMedium>
		</products>
	</RecipeDef>

	<RecipeDef ParentName="MakeshiftAnimalArmorProductionBase">
		<defName>MakeMakeshiftAnimalArmorLarge</defName>
		<label>make makeshift animal armor (large)</label>
		<description>Make a set of makeshift animal armor out of steel.\n\nFits on animals with a mature body size of 1.3 or greater, but less than 2.4.</description>
		<workAmount>10500</workAmount>
		<ingredients>
			<li>
				<filter>
					<thingDefs>
						<li>Steel</li>
					</thingDefs>
				</filter>
				<count>210</count>
			</li>
		</ingredients>
		<products>
			<MakeshiftAnimalArmorLarge>1</MakeshiftAnimalArmorLarge>
		</products>
	</RecipeDef>

	<RecipeDef ParentName="MakeshiftAnimalArmorProductionBase">
		<defName>MakeMakeshiftAnimalArmorHuge</defName>
		<label>make makeshift animal armor (huge)</label>
		<description>Make a set of makeshift animal armor out of steel.\n\nFits on animals with a mature body size of 2.4 or greater.</description>
		<workAmount>21000</workAmount>
		<ingredients>
			<li>
				<filter>
					<thingDefs>
						<li>Steel</li>
					</thingDefs>
				</filter>
				<count>420</count>
			</li>
		</ingredients>
		<products>
			<MakeshiftAnimalArmorHuge>1</MakeshiftAnimalArmorHuge>
		</products>
	</RecipeDef>

	<!-- install -->

	<RecipeDef ParentName="MakeshiftAnimalArmorInstallationBase">
		<defName>InstallMakeshiftAnimalArmorTiny</defName>
		<label>install makeshift animal armor (tiny)</label>
		<workAmount>850</workAmount>
		<ingredients>
			<li>
				<filter>
					<thingDefs>
						<li>MakeshiftAnimalArmorTiny</li>
					</thingDefs>
				</filter>
				<count>1</count>
			</li>
		</ingredients>
		<fixedIngredientFilter>
			<thingDefs>
				<li>MakeshiftAnimalArmorTiny</li>
			</thingDefs>
		</fixedIngredientFilter>
		<addsHediff>MakeshiftAnimalArmorTiny</addsHediff>
	</RecipeDef>

	<RecipeDef ParentName="MakeshiftAnimalArmorInstallationBase">
		<defName>InstallMakeshiftAnimalArmorSmall</defName>
		<label>install makeshift animal armor (small)</label>
		<workAmount>1700</workAmount>
		<ingredients>
			<li>
				<filter>
					<thingDefs>
						<li>MakeshiftAnimalArmorSmall</li>
					</thingDefs>
				</filter>
				<count>1</count>
			</li>
		</ingredients>
		<fixedIngredientFilter>
			<thingDefs>
				<li>MakeshiftAnimalArmorSmall</li>
			</thingDefs>
		</fixedIngredientFilter>
		<addsHediff>MakeshiftAnimalArmorSmall</addsHediff>
	</RecipeDef>

	<RecipeDef ParentName="MakeshiftAnimalArmorInstallationBase">
		<defName>InstallMakeshiftAnimalArmorMedium</defName>
		<label>install makeshift animal armor (medium)</label>
		<workAmount>3000</workAmount>
		<ingredients>
			<li>
				<filter>
					<thingDefs>
						<li>MakeshiftAnimalArmorMedium</li>
					</thingDefs>
				</filter>
				<count>1</count>
			</li>
		</ingredients>
		<fixedIngredientFilter>
			<thingDefs>
				<li>MakeshiftAnimalArmorMedium</li>
			</thingDefs>
		</fixedIngredientFilter>
		<addsHediff>MakeshiftAnimalArmorMedium</addsHediff>
	</RecipeDef>

	<RecipeDef ParentName="MakeshiftAnimalArmorInstallationBase">
		<defName>InstallMakeshiftAnimalArmorLarge</defName>
		<label>install makeshift animal armor (large)</label>
		<workAmount>5250</workAmount>
		<ingredients>
			<li>
				<filter>
					<thingDefs>
						<li>MakeshiftAnimalArmorLarge</li>
					</thingDefs>
				</filter>
				<count>1</count>
			</li>
		</ingredients>
		<fixedIngredientFilter>
			<thingDefs>
				<li>MakeshiftAnimalArmorLarge</li>
			</thingDefs>
		</fixedIngredientFilter>
		<addsHediff>MakeshiftAnimalArmorLarge</addsHediff>
	</RecipeDef>

	<RecipeDef ParentName="MakeshiftAnimalArmorInstallationBase">
		<defName>InstallMakeshiftAnimalArmorHuge</defName>
		<label>install makeshift animal armor (huge)</label>
		<workAmount>10500</workAmount>
		<ingredients>
			<li>
				<filter>
					<thingDefs>
						<li>MakeshiftAnimalArmorHuge</li>
					</thingDefs>
				</filter>
				<count>1</count>
			</li>
		</ingredients>
		<fixedIngredientFilter>
			<thingDefs>
				<li>MakeshiftAnimalArmorHuge</li>
			</thingDefs>
		</fixedIngredientFilter>
		<addsHediff>MakeshiftAnimalArmorHuge</addsHediff>
	</RecipeDef>

</Defs>